very_cool_converter/__init__.py
very_cool_converter/currency.py
very_cool_converter/distance.py
very_cool_converter/mass.py
very_cool_converter/temperature.py
very_cool_converter100-0.2.0.dist-info/METADATA
very_cool_converter100-0.2.0.dist-info/WHEEL
very_cool_converter100-0.2.0.dist-info/top_level.txt
very_cool_converter100-0.2.0.dist-info/RECORD
