Metadata-Version: 2.1
Name: very-cool-converter100
Version: 0.2.0
Summary: A package to convert units of distance, temperature, mass, and currency.
Author: Your Name
Author-email: your_email@example.com
Classifier: Programming Language :: Python :: 3
Classifier: License :: OSI Approved :: MIT License
Classifier: Operating System :: OS Independent
Requires-Python: >=3.6
Requires-Dist: requests
Requires-Dist: string-color
